xontrib/iterm2.py
xontrib/kitty.py
xontrib_iterm2-0.0.2.dist-info/LICENSE
xontrib_iterm2-0.0.2.dist-info/WHEEL
xontrib_iterm2-0.0.2.dist-info/METADATA
xontrib_iterm2-0.0.2.dist-info/RECORD
